MANIFEST.in
README.md
setup.py
django_reporter_pro/__init__.py
django_reporter_pro/urls.py
django_reporter_pro.egg-info/PKG-INFO
django_reporter_pro.egg-info/SOURCES.txt
django_reporter_pro.egg-info/dependency_links.txt
django_reporter_pro.egg-info/top_level.txt
django_reporter_pro/config/__init__.py
django_reporter_pro/config/model_configs.py
django_reporter_pro/controller/__init__.py
django_reporter_pro/controller/query_processor.py
django_reporter_pro/controller/dimension_processor/__init__.py
django_reporter_pro/controller/dimension_processor/process_dimensions.py
django_reporter_pro/controller/filter_processor/__init__.py
django_reporter_pro/controller/filter_processor/process_filters.py
django_reporter_pro/controller/measure_processor/__init__.py
django_reporter_pro/controller/measure_processor/process_measures.py
django_reporter_pro/controller/search_processor/__init__.py
django_reporter_pro/decorator/__init__.py
django_reporter_pro/decorator/enable_for_reporter.py
django_reporter_pro/enums/__init__.py
django_reporter_pro/enums/enum_mixin.py
django_reporter_pro/extensions/__init__.py
django_reporter_pro/extensions/basic/__init__.py
django_reporter_pro/extensions/basic/stringification.py
django_reporter_pro/extensions/django/__init__.py
django_reporter_pro/extensions/django/db/__init__.py
django_reporter_pro/extensions/django/db/models/__init__.py
django_reporter_pro/extensions/django/db/models/expressions.py
django_reporter_pro/extensions/django/db/models/functions/__init__.py
django_reporter_pro/extensions/django/db/models/functions/postgresql/__init__.py
django_reporter_pro/extensions/django/db/models/functions/postgresql/timestamp.py
django_reporter_pro/extensions/django/db/models/sql/__init__.py
django_reporter_pro/extensions/django/db/models/sql/jsonb_datastructure.py
django_reporter_pro/extensions/handlers/__init__.py
django_reporter_pro/extensions/handlers/json_handler.py
django_reporter_pro/extensions/handlers/time_handler.py
django_reporter_pro/extensions/rest_framework/__init__.py
django_reporter_pro/extensions/rest_framework/fields/__init__.py
django_reporter_pro/management/__init__.py
