Metadata-Version: 2.1
Name: django-reporter-pro
Version: 2020.1.8.1
Summary: Django report builder pro
Home-page: https://github.com/shamilison/django-reporter-pro
Author: Shamil Sakib
Author-email: shamilsakib@gmail.com
License: Other/Proprietary License
Platform: UNKNOWN
Classifier: Environment :: Web Environment
Classifier: Framework :: Django
Classifier: Framework :: Django :: 1.11
Classifier: Intended Audience :: Developers
Classifier: License :: Other/Proprietary License
Classifier: Operating System :: OS Independent
Classifier: Programming Language :: Python
Classifier: Programming Language :: Python :: 3
Classifier: Programming Language :: Python :: 3.7
Classifier: Topic :: Internet :: WWW/HTTP
Classifier: Topic :: Internet :: WWW/HTTP :: Dynamic Content
